lipyds-0.0.1.dist-info/top_level.txt
lipyds-0.0.1.dist-info/RECORD
lipyds-0.0.1.dist-info/LICENSE
lipyds-0.0.1.dist-info/METADATA
lipyds-0.0.1.dist-info/WHEEL
lipyds/__init__.py
lipyds/data/__init__.py
lipyds/data/lipid_classes.py
lipyds/tests/test_leafletfinder_legacy.py
lipyds/tests/__init__.py
lipyds/tests/datafiles.py
lipyds/tests/test_leafletfinder.py
lipyds/tests/data/glyt2_neuronal.gro
lipyds/tests/data/surface_points.dat
lipyds/tests/data/hdat_neuronal.gro
lipyds/tests/data/martini_double_bilayer.gro
lipyds/tests/data/dDAT_POPC-CHOL_r1_nowater.tpr
lipyds/tests/data/fatslim_dppc_vesicle_plus.gro
lipyds/tests/data/hsert_neuronal.gro
lipyds/tests/data/ddat_neuronal.gro
lipyds/tests/data/dDAT_POPC-CHOL_r1_10ns.xtc
lipyds/tests/data/fatslim_dppc_vesicle.pdb
lipyds/lib/utils.py
lipyds/lib/cutils.cpp
lipyds/lib/cutils.pyx
lipyds/lib/cutils.cpython-312-x86_64-linux-gnu.so
lipyds/lib/mdautils.py
lipyds/lib/__init__.py
lipyds/lib/include/pbcutils.h
lipyds/core/__init__.py
lipyds/core/topologyattrs.py
lipyds/leafletfinder/grouping.py
lipyds/leafletfinder/leafletfinder.py
lipyds/leafletfinder/__init__.py
lipyds/utils/__init__.py
lipyds/utils/guessing.py
