Metadata-Version: 2.1
Name: lipyds
Version: 0.0.1
Summary: A toolkit for leaflet-based membrane analysis
Author: Lily Wang
Author-email: Lily Wang <lily@mdanalysis.org>
Maintainer-email: Lily Wang <lily@mdanalysis.org>
License: GNU LESSER GENERAL PUBLIC LICENSE
Keywords: molecular simulations
Platform: Linux
Platform: Mac OS-X
Platform: Unix
Platform: Windows
Requires-Python: >=3.10
License-File: LICENSE
Requires-Dist: MDAnalysis>=2.0.0
Provides-Extra: test
Requires-Dist: pytest>=6.0; extra == "test"
Requires-Dist: pytest-xdist>=2.5; extra == "test"
Requires-Dist: pytest-cov>=3.0; extra == "test"
Provides-Extra: doc
Requires-Dist: sphinx; extra == "doc"
Requires-Dist: sphinx_rtd_theme; extra == "doc"
